{
    "$id": "https://schema.beyondallreason.dev/tachyon/lobby/addBot/response.json",
    "$schema": "http://json-schema.org/draft-07/schema#",
    "title": "LobbyAddBotResponse",
    "tachyon": {
        "source": "server",
        "target": "user",
        "scopes": ["tachyon.lobby"]
    },
    "anyOf": [
        {
            "title": "LobbyAddBotOkResponse",
            "type": "object",
            "properties": {
                "type": { "const": "response" },
                "messageId": { "type": "string" },
                "commandId": { "const": "lobby/addBot" },
                "status": { "const": "success" },
                "data": {
                    "title": "LobbyAddBotOkResponseData",
                    "type": "object",
                    "properties": {
                        "id": {
                            "description": "The id the server generated for this bot",
                            "type": "string"
                        }
                    },
                    "required": ["id"]
                }
            },
            "required": ["type", "messageId", "commandId", "status", "data"]
        },
        {
            "title": "LobbyAddBotFailResponse",
            "type": "object",
            "properties": {
                "type": { "const": "response" },
                "messageId": { "type": "string" },
                "commandId": { "const": "lobby/addBot" },
                "status": { "const": "failed" },
                "reason": {
                    "enum": [
                        "not_in_lobby",
                        "ally_team_full",
                        "internal_error",
                        "unauthorized",
                        "invalid_request",
                        "command_unimplemented"
                    ]
                },
                "details": { "type": "string" }
            },
            "required": ["type", "messageId", "commandId", "status", "reason"]
        }
    ]
}
